[{"Points":[{"X":4,"Y":1120},{"X":1370,"Y":1018},{"X":2822,"Y":892},{"X":3397,"Y":832},{"X":5535,"Y":602},{"X":8159,"Y":300},{"X":10193,"Y":115},{"X":11455,"Y":49},{"X":12021,"Y":15}],"MinX":4,"MaxX":12021,"VehicleID":"871c64b8-1f36-4de5-9ba4-ea644b769a8b","PointsCount":9},{"Points":[{"X":230,"Y":1126},{"X":1303,"Y":1080},{"X":3064,"Y":957},{"X":3839,"Y":882},{"X":6428,"Y":594},{"X":7647,"Y":435},{"X":8822,"Y":305},{"X":10156,"Y":171},{"X":11040,"Y":104},{"X":11938,"Y":56},{"X":12570,"Y":13}],"MinX":230,"MaxX":12570,"VehicleID":"231f6c07-58d2-428a-97d8-1cf27600745f","PointsCount":11},{"Points":[{"X":1,"Y":813},{"X":835,"Y":898}],"MinX":1,"MaxX":835,"VehicleID":"e2ba9a67-edad-4fdc-9725-2ca60eca29a5","PointsCount":2},{"Points":[{"X":2,"Y":447},{"X":1704,"Y":222},{"X":2455,"Y":140},{"X":4297,"Y":12}],"MinX":2,"MaxX":4297,"VehicleID":"9e407bb1-e75a-4edb-ace4-512c0577cc79","PointsCount":4},{"Points":[{"X":475,"Y":340},{"X":1403,"Y":470},{"X":1786,"Y":526},{"X":3275,"Y":729},{"X":4054,"Y":834},{"X":4690,"Y":912},{"X":5452,"Y":993}],"MinX":475,"MaxX":5452,"VehicleID":"e57678b0-1e6a-4597-8c01-5348b57bb688","PointsCount":7},{"Points":[{"X":4,"Y":520},{"X":503,"Y":459},{"X":728,"Y":418},{"X":1382,"Y":350},{"X":2432,"Y":232},{"X":3294,"Y":146},{"X":4320,"Y":75},{"X":4668,"Y":50},{"X":4998,"Y":20},{"X":5107,"Y":14}],"MinX":4,"MaxX":5107,"VehicleID":"a6c13ebb-dc9d-4ba7-873f-a747767c2f1c","PointsCount":10},{"Points":[{"X":2,"Y":1077},{"X":267,"Y":1054},{"X":2271,"Y":881},{"X":3408,"Y":774},{"X":5083,"Y":598},{"X":7362,"Y":339},{"X":9882,"Y":113},{"X":10699,"Y":67},{"X":11559,"Y":15}],"MinX":2,"MaxX":11559,"VehicleID":"7518958c-b963-4db2-bee6-8ae1fc14b50e","PointsCount":9},{"Points":[{"X":4658,"Y":1133},{"X":5704,"Y":1062},{"X":7263,"Y":934},{"X":7881,"Y":868},{"X":9379,"Y":714},{"X":10318,"Y":605},{"X":11763,"Y":426},{"X":13136,"Y":279},{"X":14646,"Y":136},{"X":15088,"Y":111},{"X":15424,"Y":79},{"X":15646,"Y":77},{"X":15989,"Y":51}],"MinX":4658,"MaxX":15989,"VehicleID":"8e5c967c-c8b3-4294-9257-85910f1d648a","PointsCount":13},{"Points":[{"X":14446,"Y":1140},{"X":15012,"Y":1110},{"X":15860,"Y":1052}],"MinX":14446,"MaxX":15860,"VehicleID":"6690e7cb-cb7e-4700-80bd-552a9ba3a3cf","PointsCount":3},{"Points":[{"X":1842,"Y":98},{"X":2255,"Y":123},{"X":2755,"Y":173},{"X":5669,"Y":502},{"X":7986,"Y":779},{"X":9731,"Y":969}],"MinX":1842,"MaxX":9731,"VehicleID":"7ea4fa97-e9e8-4114-8445-b24bb49e9e5e","PointsCount":6},{"Points":[{"X":1729,"Y":1091},{"X":2530,"Y":1040},{"X":3081,"Y":998},{"X":4031,"Y":918},{"X":4428,"Y":887},{"X":5066,"Y":820},{"X":6520,"Y":661},{"X":7054,"Y":597},{"X":8301,"Y":450}],"MinX":1729,"MaxX":8301,"VehicleID":"9f1d4a22-729a-4524-ace3-d78420e19522","PointsCount":9},{"Points":[{"X":12463,"Y":1141},{"X":13327,"Y":1085},{"X":13791,"Y":1058},{"X":15748,"Y":895},{"X":15992,"Y":869}],"MinX":12463,"MaxX":15992,"VehicleID":"c98fd57f-1ded-48b1-bd14-c1f82a89531d","PointsCount":5},{"Points":[{"X":12771,"Y":1145},{"X":13558,"Y":1099},{"X":14372,"Y":1048},{"X":15337,"Y":969},{"X":15993,"Y":895}],"MinX":12771,"MaxX":15993,"VehicleID":"5c8fd292-497e-4970-9cb9-de9989845e2a","PointsCount":5},{"Points":[{"X":6287,"Y":88},{"X":7279,"Y":161},{"X":7792,"Y":204},{"X":7921,"Y":214}],"MinX":6287,"MaxX":7921,"VehicleID":"8d9ef9fb-d9dd-42b8-9823-33d650ad9ae0","PointsCount":4},{"Points":[{"X":5928,"Y":100},{"X":5928,"Y":100},{"X":6161,"Y":115},{"X":7350,"Y":203}],"MinX":5928,"MaxX":7350,"VehicleID":"9fcc7f93-8c3a-4815-bb78-d8c94b124334","PointsCount":4},{"Points":[{"X":31,"Y":383},{"X":1058,"Y":520},{"X":2736,"Y":749},{"X":3779,"Y":892}],"MinX":31,"MaxX":3779,"VehicleID":"91d2db1b-303d-4f4d-867a-5361b62b23f8","PointsCount":4},{"Points":[{"X":9579,"Y":1139},{"X":11577,"Y":1003},{"X":12000,"Y":968},{"X":12873,"Y":890},{"X":13511,"Y":822},{"X":14808,"Y":678},{"X":15996,"Y":522}],"MinX":9579,"MaxX":15996,"VehicleID":"dac23e1d-6419-44f7-8ec2-0e5032b706be","PointsCount":7},{"Points":[{"X":10009,"Y":1136},{"X":10811,"Y":1087},{"X":12956,"Y":923},{"X":15874,"Y":601}],"MinX":10009,"MaxX":15874,"VehicleID":"d91c3c6e-50a9-4938-921f-47c11c8535a8","PointsCount":4}]